ploppie/__init__.py
ploppie/chat.py
ploppie/utility.py
ploppie/messages/__init__.py
ploppie/messages/assistant.py
ploppie/messages/dynamic.py
ploppie/messages/message.py
ploppie/messages/system.py
ploppie/messages/toolcall.py
ploppie/messages/toolresult.py
ploppie/messages/user.py
ploppie/messages/files/__init__.py
ploppie/messages/files/audio.py
ploppie/messages/files/document.py
ploppie/messages/files/image.py
ploppie-0.5.2.dist-info/LICENSE.md
ploppie-0.5.2.dist-info/METADATA
ploppie-0.5.2.dist-info/WHEEL
ploppie-0.5.2.dist-info/top_level.txt
ploppie-0.5.2.dist-info/RECORD
