Metadata-Version: 2.2
Name: ploppie
Version: 0.5.2
Summary: A high-level, stupid-simple Pythonic LiteLLM abstraction layer for implementing simple chat workflows, with tools.
Home-page: https://github.com/benbaptist/pyploppie
Author: Ben Baptist
Author-email: me@benbaptist.com
License: MIT License
Classifier: Programming Language :: Python :: 3
Classifier: License :: OSI Approved :: MIT License
Classifier: Operating System :: OS Independent
Requires-Python: >=3.7
License-File: LICENSE.md
Requires-Dist: litellm
Requires-Dist: pillow
Requires-Dist: soundfile
Requires-Dist: librosa
Dynamic: author
Dynamic: author-email
Dynamic: classifier
Dynamic: description
Dynamic: description-content-type
Dynamic: home-page
Dynamic: license
Dynamic: requires-dist
Dynamic: requires-python
Dynamic: summary
